paperboy/__init__.py
paperboy/communicator.py
paperboy/send_to_scielo.py
paperboy/send_to_server.py
paperboy/utils.py
scielo_paperboy-0.5.4.dist-info/DESCRIPTION.rst
scielo_paperboy-0.5.4.dist-info/entry_points.txt
scielo_paperboy-0.5.4.dist-info/METADATA
scielo_paperboy-0.5.4.dist-info/metadata.json
scielo_paperboy-0.5.4.dist-info/pbr.json
scielo_paperboy-0.5.4.dist-info/RECORD
scielo_paperboy-0.5.4.dist-info/top_level.txt
scielo_paperboy-0.5.4.dist-info/WHEEL
