Metadata-Version: 2.0
Name: scielo-paperboy
Version: 0.5.4
Summary: Utilitary to send Images. PDF's, Translations and XML's from the local website to stanging and production servers
Home-page: http://github.com/scieloorg/paperboy
Author: Fabio Batalha
Author-email: fabio.batalha@scielo.org
License: BSD License
Platform: UNKNOWN
Classifier: Development Status :: 4 - Beta
Classifier: Intended Audience :: Developers
Classifier: Programming Language :: Python :: 3
Classifier: Programming Language :: Python :: 2.7
Requires-Dist: paramiko (>=1.16.0)
